odoo/addons/l10n_nl_partner_salutation/README.rst
odoo/addons/l10n_nl_partner_salutation/__init__.py
odoo/addons/l10n_nl_partner_salutation/__manifest__.py
odoo/addons/l10n_nl_partner_salutation/data/res_partner_title.xml
odoo/addons/l10n_nl_partner_salutation/i18n/l10n_nl_partner_salutation.pot
odoo/addons/l10n_nl_partner_salutation/i18n/nl.po
odoo/addons/l10n_nl_partner_salutation/migrations/10.0.1.1.0/post-migration.py
odoo/addons/l10n_nl_partner_salutation/models/__init__.py
odoo/addons/l10n_nl_partner_salutation/models/res_partner.py
odoo/addons/l10n_nl_partner_salutation/models/res_partner_title.py
odoo/addons/l10n_nl_partner_salutation/static/description/icon.png
odoo/addons/l10n_nl_partner_salutation/tests/__init__.py
odoo/addons/l10n_nl_partner_salutation/tests/test_partner_salutation.py
odoo/addons/l10n_nl_partner_salutation/views/res_partner.xml
odoo/addons/l10n_nl_partner_salutation/views/res_partner_title.xml
odoo11_addon_l10n_nl_partner_salutation-11.0.1.0.0.dist-info/METADATA
odoo11_addon_l10n_nl_partner_salutation-11.0.1.0.0.dist-info/WHEEL
odoo11_addon_l10n_nl_partner_salutation-11.0.1.0.0.dist-info/top_level.txt
odoo11_addon_l10n_nl_partner_salutation-11.0.1.0.0.dist-info/RECORD
