Metadata-Version: 2.1
Name: odoo11-addon-l10n-nl-partner-salutation
Version: 11.0.1.0.0
Summary: Full salutation for partners, Dutch style
Home-page: https://github.com/oca/l10n-netherlands.git
Author: Therp BV, Odoo Community Association (OCA)
Author-email: support@odoo-community.org
License: AGPL-3
Platform: UNKNOWN
Classifier: Programming Language :: Python
Classifier: Framework :: Odoo
Classifier: License :: OSI Approved :: GNU Affero General Public License v3
Requires-Python: >=2.7, !=3.0.*, !=3.1.*, !=3.2.*, !=3.3.*, !=3.4.*
Requires-Dist: odoo11-addon-l10n-nl-partner-name
Requires-Dist: odoo11-addon-partner-contact-gender
Requires-Dist: odoo (<11.1dev,>=11.0a)
